{
  "project_info": {
    "project_number": "940645248383",
    "project_id": "cinematix-49e29",
    "storage_bucket": "cinematix-49e29.appspot.com"
  },
  "client": [
    {
      "client_info": {
        "mobilesdk_app_id": "1:940645248383:android:b3fbbae775ae4bc881be4a",
        "android_client_info": {
          "package_name": "com.example.praktikum"
        }
      },
      "oauth_client": [],
      "api_key": [
        {
          "current_key": "AIzaSyC9No90_fWvfAj-rtQbcJ9aWKofSB2GrGY"
        }
      ],
      "services": {
        "appinvite_service": {
          "other_platform_oauth_client": []
        }
      }
    }
  ],
  "configuration_version": "1"
}